BioModelsRAG/__init__.py
BioModelsRAG-0.3.5.dist-info/METADATA
BioModelsRAG-0.3.5.dist-info/WHEEL
BioModelsRAG-0.3.5.dist-info/entry_points.txt
BioModelsRAG-0.3.5.dist-info/top_level.txt
BioModelsRAG-0.3.5.dist-info/RECORD
